pspicker/__init__.py
pspicker/associator.py
pspicker/channel_map.py
pspicker/energy_snr.py
pspicker/kurtosis.py
pspicker/local_amplitude.py
pspicker/logger.py
pspicker/pick_candidate.py
pspicker/plotter.py
pspicker/polarity.py
pspicker/pspicker.py
pspicker/timer.py
pspicker/version.py
pspicker/parameters/SNR_parameters.py
pspicker/parameters/__init__.py
pspicker/parameters/associator_parameters.py
pspicker/parameters/channel_mapping_rules.py
pspicker/parameters/global_window_parameters.py
pspicker/parameters/kurtosis_parameters.py
pspicker/parameters/picker_parameters.py
pspicker/parameters/picker_run_parameters.py
pspicker/parameters/picker_station_parameters.py
pspicker/parameters/polarity_parameters.py
pspicker/parameters/station_parameters.py
pspicker/paz/GSE2.py
pspicker/paz/SAC_PAZ.py
pspicker/paz/__init__.py
pspicker/paz/paz.py
pspicker/paz/version.py
pspicker/utils/__init__.py
pspicker/utils/pick_utils.py
pspicker/utils/select_traces.py
pspicker/utils/smooth_filter.py
pspicker-0.5.1.dist-info/METADATA
pspicker-0.5.1.dist-info/WHEEL
pspicker-0.5.1.dist-info/top_level.txt
pspicker-0.5.1.dist-info/RECORD
