Metadata-Version: 2.1
Name: pspicker
Version: 0.5.1
Summary: Kurtosis-based P and S wave picker
Home-page: https://github.com/WayneCrawford/pspicker
Author: Christian Baillard
Author-email: crawford@ipgp.fr
License: UNKNOWN
Keywords: seismology
Platform: UNKNOWN
Classifier: Development Status :: 4 - Beta
Classifier: Environment :: Console
Classifier: Intended Audience :: Science/Research
Classifier: Intended Audience :: Developers
Classifier: License :: OSI Approved :: GNU General Public License v3 (GPLv3)
Classifier: Natural Language :: English
Classifier: Operating System :: OS Independent
Classifier: Programming Language :: Python :: 3
Classifier: Programming Language :: Python :: 3.6
Classifier: Topic :: Scientific/Engineering
Classifier: Topic :: Scientific/Engineering :: Physics
Requires-Python: >=3.8
Requires-Dist: obspy (>=1.2)
Requires-Dist: numpy (>=1.18)
Requires-Dist: scipy (>=1.5)
Requires-Dist: verboselogs (>=1.7)
Requires-Dist: matplotlib (>=3.2)
Requires-Dist: pyyaml (>=3.0)
Requires-Dist: jsonschema (>=2.6)
Requires-Dist: jsonref (>=0.2)
